timer/__init__.py
timer/__version__.py
timer/timer.py
timer-0.2.2.dist-info/LICENSE
timer-0.2.2.dist-info/METADATA
timer-0.2.2.dist-info/WHEEL
timer-0.2.2.dist-info/top_level.txt
timer-0.2.2.dist-info/RECORD
