Metadata-Version: 2.1
Name: timer
Version: 0.2.2
Summary: Python Code Timer
Home-page: https://github.com/LucienShui/timer
Author: Lucien Shui
Author-email: lucien@lucien.ink
License: UNKNOWN
Platform: UNKNOWN
